pymolfold/__init__.py
pymolfold/plugin.py
pymolfold/server.py
pymolfold/utils.py
pymolfold/version.py
pymolfold/example/case_study/test.py
pymolfold/gui/app.py
pymolfold/gui/ccd_keys.json
pymolfold/predictors/__init__.py
pymolfold/predictors/base.py
pymolfold/predictors/boltz.py
pymolfold/predictors/esm.py
pymolfold-0.2.12.dist-info/licenses/LICENSE
pymolfold-0.2.12.dist-info/METADATA
pymolfold-0.2.12.dist-info/WHEEL
pymolfold-0.2.12.dist-info/entry_points.txt
pymolfold-0.2.12.dist-info/top_level.txt
pymolfold-0.2.12.dist-info/RECORD
