Metadata-Version: 2.4
Name: pymolfold
Version: 0.2.12
Summary: Protein structure prediction in PyMOL
Home-page: https://github.com/JinyuanSun/PymolFold
Author: Jinyuan Sun, Yifan Deng
Author-email: Jinyuan Sun <jinyuansun98@gmail.com>, Yifan Deng <dengyifan15@gmail.com>
License: MIT
Project-URL: Homepage, https://github.com/JinyuanSun/PymolFold
Project-URL: Documentation, https://github.com/JinyuanSun/PymolFold#readme
Project-URL: Repository, https://github.com/JinyuanSun/PymolFold.git
Project-URL: Issues, https://github.com/JinyuanSun/PymolFold/issues
Keywords: protein,structure prediction,PyMOL,bioinformatics,protein folding
Classifier: Development Status :: 4 - Beta
Classifier: Intended Audience :: Science/Research
Classifier: License :: OSI Approved :: MIT License
Classifier: Programming Language :: Python :: 3
Classifier: Programming Language :: Python :: 3.7
Classifier: Programming Language :: Python :: 3.8
Classifier: Programming Language :: Python :: 3.9
Classifier: Programming Language :: Python :: 3.10
Classifier: Topic :: Scientific/Engineering :: Bio-Informatics
Requires-Python: >=3.8
License-File: LICENSE
Requires-Dist: requests>=2.25.0
Requires-Dist: numpy>=1.19.0
Requires-Dist: httpx>=0.24.0
Requires-Dist: fastapi>=0.68.0
Requires-Dist: matplotlib>=3.3.0
Requires-Dist: biopython>=1.79
Requires-Dist: streamlit==1.49.1
Requires-Dist: flask==3.1.0
Requires-Dist: rdkit==2025.3.6
Requires-Dist: uvicorn==0.22.0
Requires-Dist: esm==3.2.1
Requires-Dist: torch>=2.0.0
Requires-Dist: shadowpxmeter==0.0.3
Requires-Dist: seaborn==0.13.2
Requires-Dist: python-dotenv==1.0.1
Dynamic: author
Dynamic: home-page
Dynamic: license-file
Dynamic: requires-python
